{
    "image_id": "5d35c7148ab34a68b23ece71500fd4baa0c269d1401aac6c064cf817dbf4785f",
    "image_filename": "fish_004592097447_15185.png",
    "internal_label": "Myripristis_kuntee",
    "confidence": 0.92454,
    "taxonomy_status": "verified",
    "scientific_name": "Myripristis kuntee",
    "authority": "Valenciennes, 1831",
    "aphia_id": 217915,
    "lineage": [
        {
            "rank": "Kingdom",
            "scientificname": "Animalia"
        },
        {
            "rank": "Phylum",
            "scientificname": "Chordata"
        },
        {
            "rank": "Class",
            "scientificname": "Teleostei"
        },
        {
            "rank": "Order",
            "scientificname": "Holocentriformes"
        },
        {
            "rank": "Family",
            "scientificname": "Holocentridae"
        },
        {
            "rank": "Genus",
            "scientificname": "Myripristis"
        },
        {
            "rank": "Species",
            "scientificname": "Myripristis kuntee"
        }
    ],
    "timestamp": "2026-05-10T08:15:30.043397",
    "model_version": "best_model.pth",
    "source_dataset": "Fish4Knowledge"
}